{
  "AWSTemplateFormatVersion": "2010-09-09",
  "Description": "The AWS CloudFormation template for this Serverless application",
  "Resources": {
    "ServerlessDeploymentBucket": {
      "Type": "AWS::S3::Bucket",
      "Properties": {
        "BucketEncryption": {
          "ServerSideEncryptionConfiguration": [
            {
              "ServerSideEncryptionByDefault": {
                "SSEAlgorithm": "AES256"
              }
            }
          ]
        }
      }
    },
    "ServerlessDeploymentBucketPolicy": {
      "Type": "AWS::S3::BucketPolicy",
      "Properties": {
        "Bucket": {
          "Ref": "ServerlessDeploymentBucket"
        },
        "PolicyDocument": {
          "Statement": [
            {
              "Action": "s3:*",
              "Effect": "Deny",
              "Principal": "*",
              "Resource": [
                {
                  "Fn::Join": [
                    "",
                    [
                      "arn:",
                      {
                        "Ref": "AWS::Partition"
                      },
                      ":s3:::",
                      {
                        "Ref": "ServerlessDeploymentBucket"
                      },
                      "/*"
                    ]
                  ]
                },
                {
                  "Fn::Join": [
                    "",
                    [
                      "arn:",
                      {
                        "Ref": "AWS::Partition"
                      },
                      ":s3:::",
                      {
                        "Ref": "ServerlessDeploymentBucket"
                      }
                    ]
                  ]
                }
              ],
              "Condition": {
                "Bool": {
                  "aws:SecureTransport": false
                }
              }
            }
          ]
        }
      }
    },
    "IndexLogGroup": {
      "Type": "AWS::Logs::LogGroup",
      "Properties": {
        "LogGroupName": "/aws/lambda/f1-bot"
      }
    },
    "IamRoleLambdaExecution": {
      "Type": "AWS::IAM::Role",
      "Properties": {
        "AssumeRolePolicyDocument": {
          "Version": "2012-10-17",
          "Statement": [
            {
              "Effect": "Allow",
              "Principal": {
                "Service": [
                  "lambda.amazonaws.com"
                ]
              },
              "Action": [
                "sts:AssumeRole"
              ]
            }
          ]
        },
        "Policies": [
          {
            "PolicyName": {
              "Fn::Join": [
                "-",
                [
                  "f1-bot",
                  "dev",
                  "lambda"
                ]
              ]
            },
            "PolicyDocument": {
              "Version": "2012-10-17",
              "Statement": [
                {
                  "Effect": "Allow",
                  "Action": [
                    "logs:CreateLogStream",
                    "logs:CreateLogGroup",
                    "logs:TagResource"
                  ],
                  "Resource": [
                    {
                      "Fn::Sub": "arn:${AWS::Partition}:logs:${AWS::Region}:${AWS::AccountId}:log-group:/aws/lambda/f1-bot:*"
                    }
                  ]
                },
                {
                  "Effect": "Allow",
                  "Action": [
                    "logs:PutLogEvents"
                  ],
                  "Resource": [
                    {
                      "Fn::Sub": "arn:${AWS::Partition}:logs:${AWS::Region}:${AWS::AccountId}:log-group:/aws/lambda/f1-bot:*:*"
                    }
                  ]
                }
              ]
            }
          }
        ],
        "Path": "/",
        "RoleName": {
          "Fn::Join": [
            "-",
            [
              "f1-bot",
              "dev",
              {
                "Ref": "AWS::Region"
              },
              "lambdaRole"
            ]
          ]
        }
      }
    },
    "IndexLambdaFunction": {
      "Type": "AWS::Lambda::Function",
      "Properties": {
        "Code": {
          "S3Bucket": {
            "Ref": "ServerlessDeploymentBucket"
          },
          "S3Key": "serverless/f1-bot/dev/1723062932878-2024-08-07T20:35:32.878Z/index.zip"
        },
        "Handler": "lambda.handler",
        "Runtime": "python3.10",
        "FunctionName": "f1-bot",
        "MemorySize": 128,
        "Timeout": 10,
        "Description": "F1 Bot Lambda",
        "Role": {
          "Fn::GetAtt": [
            "IamRoleLambdaExecution",
            "Arn"
          ]
        }
      },
      "DependsOn": [
        "IndexLogGroup"
      ]
    },
    "IndexLambdaVersionRtszU0Ix88JN0LZ4ILJWWaI2ptLQZRHzmW0XJhiQxyg": {
      "Type": "AWS::Lambda::Version",
      "DeletionPolicy": "Retain",
      "Properties": {
        "FunctionName": {
          "Ref": "IndexLambdaFunction"
        },
        "CodeSha256": "OnSgLXV+XuT/asa/VqATQnva7wvtFk/+Z52dLXWGHIU=",
        "Description": "F1 Bot Lambda"
      }
    }
  },
  "Outputs": {
    "ServerlessDeploymentBucketName": {
      "Value": {
        "Ref": "ServerlessDeploymentBucket"
      },
      "Export": {
        "Name": "sls-f1-bot-dev-ServerlessDeploymentBucketName"
      }
    },
    "IndexLambdaFunctionQualifiedArn": {
      "Description": "Current Lambda function version",
      "Value": {
        "Ref": "IndexLambdaVersionRtszU0Ix88JN0LZ4ILJWWaI2ptLQZRHzmW0XJhiQxyg"
      },
      "Export": {
        "Name": "sls-f1-bot-dev-IndexLambdaFunctionQualifiedArn"
      }
    }
  }
}